algebraeon/__init__.py
algebraeon/algebraeon.cpython-313-i386-linux-musl.so
algebraeon-0.0.2.dist-info/METADATA
algebraeon-0.0.2.dist-info/WHEEL
algebraeon.libs/libgcc_s-f5fcfe20.so.1
algebraeon-0.0.2.dist-info/RECORD
