Metadata-Version: 2.4
Name: algebraeon
Version: 0.0.2
Classifier: Programming Language :: Rust
Classifier: Programming Language :: Python :: Implementation :: CPython
Classifier: Programming Language :: Python :: Implementation :: PyPy
Classifier: Development Status :: 1 - Planning
Summary: A Pythonic wrapper around the Rust library Algebraeon for computational algebra.
Keywords: math,maths,algebra,polynomial,matrix,linear algebra,factoring,algebraic number
License-Expression: GPL-3.0-only
Requires-Python: >=3.8
